MissingValues_Arsh/__init__.py
MissingValues_Arsh/__main__.py
MissingValues_Arsh-0.0.2.dist-info/LICENSE.txt
MissingValues_Arsh-0.0.2.dist-info/METADATA
MissingValues_Arsh-0.0.2.dist-info/WHEEL
MissingValues_Arsh-0.0.2.dist-info/top_level.txt
MissingValues_Arsh-0.0.2.dist-info/RECORD
