Metadata-Version: 2.1
Name: MissingValues-Arsh
Version: 0.0.2
Summary: Treating Missing values in a dataset
Home-page: UNKNOWN
Author: Arshpreet Singh
Author-email: asingh9_be17@thapar.edu
License: UNKNOWN
Platform: UNKNOWN
Classifier: Programming Language :: Python :: 3
Classifier: License :: OSI Approved :: MIT License
Classifier: Operating System :: OS Independent
Requires-Python: >=3.6
